cc_statusline/__init__.py
cc_statusline/__main__.py
cc_statusline/cli/__init__.py
cc_statusline/cli/commands.py
cc_statusline/config/__init__.py
cc_statusline/config/installer.py
cc_statusline/config/interactive.py
cc_statusline/core/__init__.py
cc_statusline/engine/__init__.py
cc_statusline/engine/scheduler.py
cc_statusline/engine/statusline_engine.py
cc_statusline/modules/__init__.py
cc_statusline/modules/base.py
cc_statusline/modules/basic.py
cc_statusline/modules/cost.py
cc_statusline/modules/mcp_status.py
cc_statusline/modules/model.py
cc_statusline/modules/realtime.py
cc_statusline/modules/registry.py
cc_statusline/modules/session_time.py
cc_statusline/modules/time_modules.py
cc_statusline/render/__init__.py
cc_statusline/render/powerline.py
cc_statusline/render/terminal_renderer.py
cc_statusline/theme/__init__.py
cc_statusline/theme/builtins.py
cc_statusline/theme/loader.py
cc_status-0.0.3.dist-info/METADATA
cc_status-0.0.3.dist-info/WHEEL
cc_status-0.0.3.dist-info/entry_points.txt
cc_status-0.0.3.dist-info/licenses/LICENSE
cc_status-0.0.3.dist-info/RECORD
