Metadata-Version: 2.4
Name: cc-status
Version: 0.0.3
Summary: Claude Code 状态栏功能模块
Project-URL: Homepage, https://github.com/michaelche/cc-statusline
Project-URL: Documentation, https://github.com/michaelche/cc-statusline#readme
Project-URL: Repository, https://github.com/michaelche/cc-statusline.git
Project-URL: Issues, https://github.com/michaelche/cc-statusline/issues
Project-URL: Changelog, https://github.com/michaelche/cc-statusline/blob/main/CHANGELOG.md
Author-email: Michael Che <michaelche@example.com>
License: Apache-2.0
License-File: LICENSE
Keywords: claude-code,cli,statusline
Classifier: Development Status :: 4 - Beta
Classifier: Environment :: Console
Classifier: Intended Audience :: Developers
Classifier: License :: OSI Approved :: Apache Software License
Classifier: Operating System :: OS Independent
Classifier: Programming Language :: Python :: 3
Classifier: Programming Language :: Python :: 3.9
Classifier: Programming Language :: Python :: 3.10
Classifier: Programming Language :: Python :: 3.11
Classifier: Programming Language :: Python :: 3.12
Classifier: Topic :: Software Development :: Libraries :: Python Modules
Requires-Python: >=3.9
Requires-Dist: httpx>=0.25.0
Requires-Dist: prompt-toolkit>=3.0.0
Requires-Dist: psutil>=5.9.0
Requires-Dist: pyyaml>=6.0
Provides-Extra: dev
Requires-Dist: black>=23.7.0; extra == 'dev'
Requires-Dist: mypy>=1.4.1; extra == 'dev'
Requires-Dist: pytest-cov>=4.1.0; extra == 'dev'
Requires-Dist: pytest>=7.4.0; extra == 'dev'
Requires-Dist: ruff>=0.0.280; extra == 'dev'
Requires-Dist: types-pyyaml>=6.0.0; extra == 'dev'
